__init__.py
ipTiger.py
test.py
ipTiger-0.0.1.dist-info/LICENSE.txt
ipTiger-0.0.1.dist-info/METADATA
ipTiger-0.0.1.dist-info/WHEEL
ipTiger-0.0.1.dist-info/top_level.txt
ipTiger-0.0.1.dist-info/RECORD
