Metadata-Version: 2.1
Name: ipTiger
Version: 0.0.1
Summary: ipTiger is an python package for find ip address details such as country name, city name, latitude and longitude etc.
Author-email: FARHAN AHMED <contact@farhyn.com>
Project-URL: Homepage, https://github.com/MDFARHYN/ipTiger
Project-URL: Bug Tracker, https://github.com/MDFARHYN/ipTiger/issues
Keywords: ipTiger,ip tiger,ipaddress,farhyn.com,proxy,check ip address,what is my ip address,find my ip address,ip details
Classifier: Programming Language :: Python :: 3
Classifier: License :: OSI Approved :: MIT License
Classifier: Operating System :: OS Independent
Requires-Python: >=3.7
License-File: LICENSE.txt
Requires-Dist: bs4
Requires-Dist: requests
